chemname/__init__.py
chemname/chem.py
chemname-0.0.3.dist-info/LICENSE
chemname-0.0.3.dist-info/METADATA
chemname-0.0.3.dist-info/WHEEL
chemname-0.0.3.dist-info/top_level.txt
chemname-0.0.3.dist-info/RECORD
