Metadata-Version: 2.1
Name: chemname
Version: 0.0.3
Summary: A tool to convert any text to chemical names, where possible.
Author-email: lancylot <lancylot2004@proton.me>
License: MIT License        
Project-URL: Homepage, https://github.com/lancylot2004/Chemname
Project-URL: Bug Tracker, https://github.com/lancylot2004/Chemname/issues
Keywords: chemistry,name,chemical
Classifier: Programming Language :: Python :: 3
Classifier: License :: OSI Approved :: MIT License
Classifier: Operating System :: OS Independent
Requires-Python: >=3.7
License-File: LICENSE
